green_bacon_sandals/__init__.py
green_bacon_sandals/green_bacon_sandals.py
green_bacon_sandals-0.2.dist-info/LICENSE
green_bacon_sandals-0.2.dist-info/METADATA
green_bacon_sandals-0.2.dist-info/WHEEL
green_bacon_sandals-0.2.dist-info/top_level.txt
green_bacon_sandals-0.2.dist-info/RECORD
