Metadata-Version: 2.1
Name: green-bacon-sandals
Version: 0.2
Summary: Get random image from google images
Home-page: https://github.com/atomicfruitcake/green-bacon-sandals
Author: Sam Bass
Author-email: sam@wirewax.com
License: MIT
Download-URL: https://github.com/atomicfruitcake/green-bacon-sandals/archive/0.2.tar.gz
Keywords: google,images,bacon
Platform: UNKNOWN
Classifier: Development Status :: 3 - Alpha
Classifier: Intended Audience :: Developers
Classifier: License :: OSI Approved :: MIT License
Classifier: Programming Language :: Python :: 2
Classifier: Programming Language :: Python :: 2.6
Classifier: Programming Language :: Python :: 2.7
Classifier: Programming Language :: Python :: 3
Classifier: Programming Language :: Python :: 3.2
Classifier: Programming Language :: Python :: 3.3
Classifier: Programming Language :: Python :: 3.4
Classifier: Programming Language :: Python :: 3.5
Classifier: Programming Language :: Python :: 3.6
Classifier: Programming Language :: Python :: 3.7
Requires-Dist: apiclient
